jupyterlab_sql_editor/__init__.py
jupyterlab_sql_editor/_version.py
jupyterlab_sql_editor/ipython_magic/__init__.py
jupyterlab_sql_editor/ipython_magic/base.py
jupyterlab_sql_editor/ipython_magic/export.py
jupyterlab_sql_editor/ipython_magic/messages.py
jupyterlab_sql_editor/ipython_magic/result_cache.py
jupyterlab_sql_editor/ipython_magic/sql-language-server.schema.json
jupyterlab_sql_editor/ipython_magic/util.py
jupyterlab_sql_editor/ipython_magic/sparksql/__init__.py
jupyterlab_sql_editor/ipython_magic/sparksql/balls_line.gif
jupyterlab_sql_editor/ipython_magic/sparksql/main.py
jupyterlab_sql_editor/ipython_magic/sparksql/spark_export.py
jupyterlab_sql_editor/ipython_magic/sparksql/spark_schema_widget.py
jupyterlab_sql_editor/ipython_magic/sparksql/spark_streaming_query.py
jupyterlab_sql_editor/ipython_magic/sparksql/sparkdf.py
jupyterlab_sql_editor/ipython_magic/sparksql/sparksql.py
jupyterlab_sql_editor/ipython_magic/trino/__init__.py
jupyterlab_sql_editor/ipython_magic/trino/main.py
jupyterlab_sql_editor/ipython_magic/trino/trino.py
jupyterlab_sql_editor/ipython_magic/trino/trino_export.py
jupyterlab_sql_editor/ipython_magic/trino/trino_schema_widget.py
jupyterlab_sql_editor/outputters/__init__.py
jupyterlab_sql_editor/outputters/outputters.py
jupyterlab_sql_editor/outputters/util.py
jupyterlab_sql_editor-1.9.2.data/data/jupyterlab_sql_editor/ipython_magic/sql-language-server.schema.json
jupyterlab_sql_editor-1.9.2.data/data/share/jupyter/labextensions/jupyterlab-sql-editor/package.json
jupyterlab_sql_editor-1.9.2.data/data/share/jupyter/labextensions/jupyterlab-sql-editor/schemas/jupyterlab-sql-editor/package.json.orig
jupyterlab_sql_editor-1.9.2.data/data/share/jupyter/labextensions/jupyterlab-sql-editor/schemas/jupyterlab-sql-editor/plugin.json
jupyterlab_sql_editor-1.9.2.data/data/share/jupyter/labextensions/jupyterlab-sql-editor/static/277.c7f93e45bddf9ead2853.js
jupyterlab_sql_editor-1.9.2.dist-info/METADATA
jupyterlab_sql_editor-1.9.2.dist-info/WHEEL
jupyterlab_sql_editor-1.9.2.dist-info/entry_points.txt
jupyterlab_sql_editor-1.9.2.dist-info/licenses/LICENSE
jupyterlab_sql_editor-1.9.2.dist-info/RECORD
