Metadata-Version: 2.4
Name: jupyterlab_sql_editor
Version: 1.9.2
Dynamic: Keywords
Summary: SQL editor support for formatting, syntax highlighting and code completion of SQL in cell magic, line magic, python string and file editor.
Project-URL: Homepage, https://github.com/CybercentreCanada/jupyterlab-sql-editor
Project-URL: Bug Tracker, https://github.com/CybercentreCanada/jupyterlab-sql-editor/issues
Project-URL: Repository, https://github.com/CybercentreCanada/jupyterlab-sql-editor.git
Author-email: CybercentreCanada <contact@cyber.gc.ca>
License: BSD 3-Clause License
License-File: LICENSE
Classifier: Framework :: Jupyter
Classifier: Framework :: Jupyter :: JupyterLab
Classifier: Framework :: Jupyter :: JupyterLab :: 4
Classifier: Framework :: Jupyter :: JupyterLab :: Extensions
Classifier: Framework :: Jupyter :: JupyterLab :: Extensions :: Prebuilt
Classifier: License :: OSI Approved :: BSD License
Classifier: Programming Language :: Python
Classifier: Programming Language :: Python :: 3
Classifier: Programming Language :: Python :: 3.8
Classifier: Programming Language :: Python :: 3.9
Classifier: Programming Language :: Python :: 3.10
Classifier: Programming Language :: Python :: 3.11
Classifier: Programming Language :: Python :: 3.12
Requires-Python: >=3.8
Requires-Dist: cccs-ipyaggrid>=0.5.3
Requires-Dist: ipydatagrid
Requires-Dist: ipytree
Requires-Dist: ipywidgets
Requires-Dist: jinja2
Requires-Dist: jupyter-events>=0.6.1
Requires-Dist: jupyter-lsp>=2.2.0
Requires-Dist: jupyterlab-lsp>=5.0.0
Requires-Dist: pandas>=1.4.4
Requires-Dist: ply
Requires-Dist: python-lsp-server[all]
Requires-Dist: sqlalchemy
Requires-Dist: sqlglot[rs]
Requires-Dist: sqlparse
Provides-Extra: all
Requires-Dist: pyspark; extra == 'all'
Requires-Dist: trino; extra == 'all'
Provides-Extra: pyspark
Requires-Dist: pyspark; extra == 'pyspark'
Provides-Extra: trino
Requires-Dist: trino; extra == 'trino'
